slsd/__init__.py
slsd/config.py
slsd/dbus.py
slsd/lastfm.py
slsd/main.py
slsd-0.1.0.dist-info/licenses/LICENSE
slsd-0.1.0.dist-info/WHEEL
slsd-0.1.0.dist-info/entry_points.txt
slsd-0.1.0.dist-info/METADATA
slsd-0.1.0.dist-info/RECORD
