Metadata-Version: 2.4
Name: slsd
Version: 0.1.0
Summary: Simple Last.fm Scrobbling Daemon
License-Expression: MIT
License-File: LICENSE
Classifier: Programming Language :: Python :: 3
Classifier: Operating System :: POSIX :: Linux
Requires-Dist: dbus-next>=0.2.3
Requires-Dist: pylast>=5.5.0
Requires-Dist: pytest>=8.4.2
Requires-Dist: typer>=0.20.0
Requires-Python: >=3.11
Project-URL: Homepage, https://github.com/coolport/slsd
